linkd/__init__.py
linkd/compose.py
linkd/conditions.py
linkd/container.py
linkd/context.py
linkd/exceptions.py
linkd/graph.py
linkd/py.typed
linkd/registry.py
linkd/solver.py
linkd/utils.py
linkd/ext/__init__.py
linkd/ext/_common.py
linkd/ext/fastapi.py
linkd/ext/quart.py
linkd/ext/starlette.py
linkd-0.2.1.dist-info/licenses/LICENSE
linkd-0.2.1.dist-info/WHEEL
linkd-0.2.1.dist-info/METADATA
linkd-0.2.1.dist-info/RECORD
