Metadata-Version: 2.4
Name: linkd
Version: 0.2.1
Summary: A powerful async-only dependency injection framework for Python.
Keywords: ioc,dependency injection,injection,inversion of control,asyncio
Author-email: tandemdude <tandemdude1@gmail.com>
Requires-Python: >=3.10.0,<3.15
Classifier: Development Status :: 5 - Production/Stable
Classifier: License :: OSI Approved :: MIT License
Classifier: Framework :: AsyncIO
Classifier: Intended Audience :: Developers
Classifier: Natural Language :: English
Classifier: Topic :: Software Development :: Libraries :: Python Modules
Classifier: Programming Language :: Python :: 3.10
Classifier: Programming Language :: Python :: 3.11
Classifier: Programming Language :: Python :: 3.12
Classifier: Programming Language :: Python :: 3.13
Classifier: Programming Language :: Python :: Implementation :: CPython
Classifier: Programming Language :: Python :: 3 :: Only
Classifier: Topic :: Software Development :: Libraries
Classifier: Topic :: Software Development :: Libraries :: Application Frameworks
Classifier: Topic :: Software Development :: Libraries :: Python Modules
Classifier: Typing :: Typed
License-File: LICENSE
Project-URL: Changelog, https://linkd.readthedocs.io/en/latest/changelog.html
Project-URL: Documentation, https://linkd.readthedocs.io/en/latest/
Project-URL: Homepage, https://github.com/tandemdude/linkd
Project-URL: Repository, https://github.com/tandemdude/linkd
